donbeer/__init__.py
donbeer/__main__.py
donbeer/beer.py
donbeer/configuration.py
donbeer/donut.py
donbeer/game.py
donbeer/text.py
donbeer/archive/__init__.py
donbeer/archive/functional/__init__.py
donbeer/archive/functional/press.py
donbeer/archive/v1/__init__.py
donbeer/archive/v1/press.py
donbeer/resources/__init__.py
donbeer/resources/fonts/Birds.ttf
donbeer/resources/fonts/MeathFLF.ttf
donbeer/resources/fonts/__init__.py
donbeer/resources/images/__init__.py
donbeer/resources/images/beer.png
donbeer/resources/images/beer2.png
donbeer/resources/images/donut.png
donbeer/resources/images/donut2.png
donbeer-1.0.7.dist-info/LICENSE
donbeer-1.0.7.dist-info/METADATA
donbeer-1.0.7.dist-info/WHEEL
donbeer-1.0.7.dist-info/top_level.txt
donbeer-1.0.7.dist-info/RECORD
