Metadata-Version: 2.1
Name: donbeer
Version: 1.0.7
Summary: The user is able to click on a beer until a donut appears.
Home-page: https://github.com/dellumdeus/donbeer
Author: dellumdeus
Author-email: alion.develop@gmail.com
License: UNKNOWN
Platform: UNKNOWN
Classifier: Programming Language :: Python :: 3
Classifier: License :: OSI Approved :: MIT License
Classifier: Operating System :: OS Independent
Requires-Dist: pygame
